MANIFEST.in
README.md
setup.py
punittest/__init__.py
punittest/punittest.py
punittest/settings.py
punittest/statistics.py
punittest/testcase.py
punittest/testresult.py
punittest/testrunner.py
punittest/testset.py
punittest.egg-info/PKG-INFO
punittest.egg-info/SOURCES.txt
punittest.egg-info/dependency_links.txt
punittest.egg-info/requires.txt
punittest.egg-info/top_level.txt
punittest/demo/__init__.py
punittest/demo/main.py
punittest/demo/testsuite/__init__.py
punittest/demo/testsuite/buy/__init__.py
punittest/demo/testsuite/buy/test_lottery.py
punittest/demo/testsuite/buy/test_purchase.py
punittest/demo/testsuite/chat/__init__.py
punittest/demo/testsuite/chat/test_chat.py
punittest/demo/testsuite/login/__init__.py
punittest/demo/testsuite/login/test_login.py
punittest/excel_testset/TestCases.xlsx
punittest/report_template/__init__.py
punittest/report_template/style_1.py
punittest/report_template/style_2.py
punittest/static/animate.css/3.5.2/animate.min.css
punittest/static/bootstrap/3.0.3/css/bootstrap.min.css
punittest/static/bootstrap/3.0.3/js/bootstrap.min.js
punittest/static/bootstrap/3.3.5/css/bootstrap.min.css
punittest/static/bootstrap/3.3.5/js/bootstrap.min.js
punittest/static/chosen/1.8.2/chosen.css
punittest/static/chosen/1.8.2/chosen.jquery.js
punittest/static/echarts/3.8.5/echarts.min.js
punittest/static/font-awesome/4.4.0/css/font-awesome.min.css
punittest/static/jquery/2.0.0/jquery.min.js
punittest/static/jquery/2.1.4/jquery.min.js
punittest/utils/__init__.py
punittest/utils/logger.py
punittest/utils/parse_excel.py