Metadata-Version: 1.0
Name: punittest
Version: 0.1.17
Summary: An extented unittest
Home-page: http://www.google.com
Author: xiaoyao
Author-email: xiaoyaoalpha@gmail.com
License: UNKNOWN
Keywords: pip,punittest
Platform: any
